aioextensions/__init__.py
aioextensions/py.typed
test/test___init__.py
aioextensions-21.7.2261349.dist-info/LICENSE.md
aioextensions-21.7.2261349.dist-info/WHEEL
aioextensions-21.7.2261349.dist-info/METADATA
aioextensions-21.7.2261349.dist-info/RECORD
