Metadata-Version: 2.1
Name: aioextensions
Version: 21.7.2261349
Summary: High performance functions to work with the async IO
Home-page: https://fluidattacks.github.io/aioextensions
License: MIT
Author: Kevin Amado
Author-email: kamadorueda@gmail.com
Requires-Python: >=3.6,<4.0
Classifier: Development Status :: 6 - Mature
Classifier: Framework :: AsyncIO
Classifier: License :: OSI Approved :: MIT License
Classifier: Programming Language :: Python :: 3
Classifier: Programming Language :: Python :: 3.6
Classifier: Programming Language :: Python :: 3.7
Classifier: Programming Language :: Python :: 3.8
Classifier: Programming Language :: Python :: 3.9
Classifier: Topic :: Software Development :: Libraries
Classifier: Typing :: Typed
Provides-Extra: full
Requires-Dist: uvloop; extra == "full"
Project-URL: Bug Tracker, https://github.com/fluidattacks/aioextensions/issues
Project-URL: Documentation, https://fluidattacks.github.io/aioextensions
Project-URL: Repository, https://github.com/fluidattacks/aioextensions
